fpylib/__init__.py
fpylib/composer.py
fpylib/lazyness.py
fpylib/functors/__init__.py
fpylib/functors/applicative.py
fpylib/functors/flist.py
fpylib/functors/functor.py
fpylib/functors/maybe.py
fpylib/functors/monad.py
fpylib/irange/__init__.py
fpylib/irange/char_irange.py
fpylib/irange/irange.py
fpylib/irange/num_irange.py
fpylib-0.1.0.dist-info/LICENSE
fpylib-0.1.0.dist-info/METADATA
fpylib-0.1.0.dist-info/WHEEL
fpylib-0.1.0.dist-info/top_level.txt
fpylib-0.1.0.dist-info/RECORD
