Metadata-Version: 2.1
Name: fpylib
Version: 0.1.0
Summary: This is a library to do functional programming in Python.
Home-page: https://github.com/FabianVegaA/fpy_lib
Author: Fabián Vega
License: MIT
Platform: UNKNOWN
Classifier: License :: OSI Approved :: MIT License
Classifier: Programming Language :: Python :: 3
Classifier: Programming Language :: Python :: 3.8
Classifier: Programming Language :: Python :: 3.9
